[{"command": "set-logic", "logic": "QF_LIA"}, {"command": "define-system", "symbol": "CounterReset", "input": [], "output": [{"symbol": "n", "sort": {"identifier": {"symbol": "Int", "indices": []}, "parameters": []}}], "local": [], "init": {"identifier": {"symbol": "=", "indices": []}, "args": [{"identifier": "n"}, {"identifier": "10000"}]}, "trans": {"identifier": {"symbol": "=", "indices": []}, "args": [{"identifier": "n'"}, {"identifier": {"symbol": "ite", "indices": []}, "args": [{"identifier": {"symbol": "=", "indices": []}, "args": [{"identifier": "n"}, {"identifier": "0"}]}, {"identifier": "10000"}, {"identifier": {"symbol": "-", "indices": []}, "args": [{"identifier": "n"}, {"identifier": "1"}]}]}]}, "inv": {"identifier": "true"}, "subsys": []}, {"command": "check-system", "symbol": "CounterReset", "input": [], "output": [{"symbol": "n", "sort": {"identifier": {"symbol": "Int", "indices": []}, "parameters": []}}], "local": [], "assumption": [], "fairness": [], "reachable": [{"symbol": "rch", "formula": {"identifier": {"symbol": "<", "indices": []}, "args": [{"identifier": "n"}, {"identifier": "0"}]}}], "current": [], "query": [{"symbol": "q", "formulas": ["rch"]}], "queries": []}]